LICENSE.txt
MANIFEST.in
README.md
setup.cfg
setup.py
vernam/__init__.py
vernam/__main__.py
vernam/py_vernam.py
vernam.egg-info/PKG-INFO
vernam.egg-info/SOURCES.txt
vernam.egg-info/dependency_links.txt
vernam.egg-info/entry_points.txt
vernam.egg-info/requires.txt
vernam.egg-info/top_level.txt