Metadata-Version: 1.1
Name: vernam
Version: 2.5.5
Summary: Vernam cipher
Home-page: https://github.com/roysoup/Vernam
Author: Roy Siu
Author-email: UNKNOWN
License: MIT Licence
Platform: UNKNOWN
Classifier: Development Status :: 5 - Production/Stable
